{
  "hash": "2d17e206",
  "configHash": "28e31997",
  "lockfileHash": "760b6575",
  "browserHash": "e0f4a274",
  "optimized": {
    "@gsap/react": {
      "src": "../../node_modules/@gsap/react/src/index.js",
      "file": "@gsap_react.js",
      "fileHash": "353f2744",
      "needsInterop": false
    },
    "axios": {
      "src": "../../node_modules/axios/index.js",
      "file": "axios.js",
      "fileHash": "7fab5c66",
      "needsInterop": false
    },
    "clsx": {
      "src": "../../node_modules/clsx/dist/clsx.mjs",
      "file": "clsx.js",
      "fileHash": "95e9304d",
      "needsInterop": false
    },
    "framer-motion": {
      "src": "../../node_modules/framer-motion/dist/es/index.mjs",
      "file": "framer-motion.js",
      "fileHash": "a3343afd",
      "needsInterop": false
    },
    "gsap": {
      "src": "../../node_modules/gsap/index.js",
      "file": "gsap.js",
      "fileHash": "42f6f873",
      "needsInterop": false
    },
    "react-dom/client": {
      "src": "../../node_modules/react-dom/client.js",
      "file": "react-dom_client.js",
      "fileHash": "6b2b481c",
      "needsInterop": true
    },
    "react-router-dom": {
      "src": "../../node_modules/react-router-dom/dist/index.mjs",
      "file": "react-router-dom.js",
      "fileHash": "ba722afb",
      "needsInterop": false
    },
    "react": {
      "src": "../../node_modules/react/index.js",
      "file": "react.js",
      "fileHash": "51fb42ad",
      "needsInterop": true
    },
    "react/jsx-dev-runtime": {
      "src": "../../node_modules/react/jsx-dev-runtime.js",
      "file": "react_jsx-dev-runtime.js",
      "fileHash": "ba782b19",
      "needsInterop": true
    },
    "recharts": {
      "src": "../../node_modules/recharts/es6/index.js",
      "file": "recharts.js",
      "fileHash": "fc6f7b18",
      "needsInterop": false
    },
    "tailwind-merge": {
      "src": "../../node_modules/tailwind-merge/dist/bundle-mjs.mjs",
      "file": "tailwind-merge.js",
      "fileHash": "731c9a70",
      "needsInterop": false
    }
  },
  "chunks": {
    "chunk-B-1-B7_t": {
      "file": "chunk-B-1-B7_t.js",
      "isDynamicEntry": false
    },
    "gsap-DgZztMML": {
      "file": "gsap-DgZztMML.js",
      "isDynamicEntry": false
    },
    "react-dom-Br2l1Z8p": {
      "file": "react-dom-Br2l1Z8p.js",
      "isDynamicEntry": false
    }
  }
}